car_statemachine.py
crosswalk.py
trafficlight_statemachine.py
easy_patterns-0.0.1.dist-info/LICENSE
easy_patterns-0.0.1.dist-info/METADATA
easy_patterns-0.0.1.dist-info/WHEEL
easy_patterns-0.0.1.dist-info/top_level.txt
easy_patterns-0.0.1.dist-info/RECORD
