Metadata-Version: 2.1
Name: easy-patterns
Version: 0.0.1
Summary: A basic demonstrator for teaching design patterns.
Home-page: UNKNOWN
Author: Keith Helsabeck
Author-email: admin@mylawdb.com
License: UNKNOWN
Platform: UNKNOWN
Classifier: Programming Language :: Python :: 3
Classifier: Programming Language :: Python :: 3.6
Classifier: Programming Language :: Python :: 3.7
Classifier: Programming Language :: Python :: 3.8
Classifier: License :: OSI Approved :: MIT License
Classifier: Operating System :: OS Independent
